MANIFEST.in
README.md
VERSION
setup.py
pyfreelan/__init__.py
pyfreelan/main.py
pyfreelan.egg-info/PKG-INFO
pyfreelan.egg-info/SOURCES.txt
pyfreelan.egg-info/dependency_links.txt
pyfreelan.egg-info/entry_points.txt
pyfreelan.egg-info/requires.txt
pyfreelan.egg-info/top_level.txt
pyfreelan/server/__init__.py
pyfreelan/server/application/__init__.py