Metadata-Version: 1.1
Name: pyfreelan
Version: 0.0.2
Summary: Provides HTTP(S) client/server features to the FreeLAN VPN software
Home-page: http://pyfreelan.readthedocs.org/en/latest/index.html
Author: Julien Kauffmann
Author-email: julien.kauffmann@freelan.org
License: GPLv3
Platform: UNKNOWN
Classifier: Intended Audience :: Developers
Classifier: Intended Audience :: System Administrators
Classifier: Operating System :: MacOS :: MacOS X
Classifier: Operating System :: Microsoft :: Windows
Classifier: Operating System :: POSIX
Classifier: Programming Language :: Python :: 2.7
Classifier: Topic :: Software Development
Classifier: License :: OSI Approved :: GNU General Public License v3 (GPLv3)
Classifier: Development Status :: 2 - Pre-Alpha
